pythermalcomfort/__init__.py
pythermalcomfort/__main__.py
pythermalcomfort/classes_input.py
pythermalcomfort/classes_return.py
pythermalcomfort/cli.py
pythermalcomfort/shared_functions.py
pythermalcomfort/utilities.py
pythermalcomfort/jos3_functions/__init__.py
pythermalcomfort/jos3_functions/construction.py
pythermalcomfort/jos3_functions/matrix.py
pythermalcomfort/jos3_functions/parameters.py
pythermalcomfort/jos3_functions/thermoregulation.py
pythermalcomfort/models/__init__.py
pythermalcomfort/models/_pmv_ppd_optimized.py
pythermalcomfort/models/adaptive_ashrae.py
pythermalcomfort/models/adaptive_en.py
pythermalcomfort/models/ankle_draft.py
pythermalcomfort/models/at.py
pythermalcomfort/models/clo_tout.py
pythermalcomfort/models/cooling_effect.py
pythermalcomfort/models/discomfort_index.py
pythermalcomfort/models/esi.py
pythermalcomfort/models/heat_index_lu.py
pythermalcomfort/models/heat_index_rothfusz.py
pythermalcomfort/models/humidex.py
pythermalcomfort/models/jos3.py
pythermalcomfort/models/net.py
pythermalcomfort/models/pet_steady.py
pythermalcomfort/models/phs.py
pythermalcomfort/models/pmv_a.py
pythermalcomfort/models/pmv_athb.py
pythermalcomfort/models/pmv_e.py
pythermalcomfort/models/pmv_ppd_ashrae.py
pythermalcomfort/models/pmv_ppd_iso.py
pythermalcomfort/models/ridge_regression_predict_t_re_t_sk.py
pythermalcomfort/models/set_tmp.py
pythermalcomfort/models/solar_gain.py
pythermalcomfort/models/thi.py
pythermalcomfort/models/two_nodes_gagge.py
pythermalcomfort/models/two_nodes_gagge_ji.py
pythermalcomfort/models/two_nodes_gagge_sleep.py
pythermalcomfort/models/use_fans_heatwaves.py
pythermalcomfort/models/utci.py
pythermalcomfort/models/vertical_tmp_grad_ppd.py
pythermalcomfort/models/wbgt.py
pythermalcomfort/models/wci.py
pythermalcomfort/models/wind_chill_temperature.py
pythermalcomfort/models/work_capacity_dunne.py
pythermalcomfort/models/work_capacity_hothaps.py
pythermalcomfort/models/work_capacity_iso.py
pythermalcomfort-3.8.0.dist-info/licenses/AUTHORS.rst
pythermalcomfort-3.8.0.dist-info/licenses/LICENSE
pythermalcomfort-3.8.0.dist-info/METADATA
pythermalcomfort-3.8.0.dist-info/WHEEL
pythermalcomfort-3.8.0.dist-info/entry_points.txt
pythermalcomfort-3.8.0.dist-info/top_level.txt
pythermalcomfort-3.8.0.dist-info/RECORD
