Metadata-Version: 2.4
Name: pythermalcomfort
Version: 3.8.0
Summary: pythermalcomfort is a comprehensive toolkit for calculating thermal comfort indices, heat/cold stress metrics, and thermophysiological responses. It supports multiple models, including PMV, PPD, adaptive comfort, SET, UTCI, Heat Index, Wind Chill Index, and Humidex. The package also includes thermophysiological models like the two-node (Gagge) and multinode (JOS-3) models to estimate physiological responses such as core temperature, skin temperature, and skin wettedness. 
Home-page: https://github.com/CenterForTheBuiltEnvironment/pythermalcomfort
Author: Federico Tartarini
Author-email: cbecomforttool@gmail.com
License: MIT
Project-URL: Documentation, https://pythermalcomfort.readthedocs.io/
Project-URL: Changelog, https://pythermalcomfort.readthedocs.io/en/latest/changelog.html
Project-URL: Issue Tracker, https://github.com/CenterForTheBuiltEnvironment/pythermalcomfort/issues
Keywords: thermal comfort,pmv,heat stress,cold stress,thermal sensation,thermal physiology,meteorology,climate analysis,discomfort,comfort,thermal environment,built environment
Classifier: Development Status :: 5 - Production/Stable
Classifier: Intended Audience :: Developers
Classifier: Intended Audience :: Education
Classifier: Intended Audience :: Science/Research
Classifier: License :: OSI Approved :: MIT License
Classifier: Operating System :: Unix
Classifier: Operating System :: POSIX
Classifier: Operating System :: Microsoft :: Windows
Classifier: Programming Language :: Python
Classifier: Programming Language :: Python :: 3
Classifier: Programming Language :: Python :: 3.10
Classifier: Programming Language :: Python :: 3.11
Classifier: Programming Language :: Python :: 3.12
Classifier: Programming Language :: Python :: 3.13
Classifier: Programming Language :: Python :: Implementation :: CPython
Classifier: Programming Language :: Python :: Implementation :: PyPy
Classifier: Topic :: Education
Classifier: Topic :: Scientific/Engineering
Classifier: Topic :: Scientific/Engineering :: Atmospheric Science
Classifier: Topic :: Utilities
Requires-Python: >=3.10.0
License-File: LICENSE
License-File: AUTHORS.rst
Requires-Dist: scipy
Requires-Dist: numba
Requires-Dist: numpy
Requires-Dist: setuptools
Provides-Extra: dev
Requires-Dist: pytest; extra == "dev"
Requires-Dist: sphinx; extra == "dev"
Dynamic: author
Dynamic: author-email
Dynamic: classifier
Dynamic: description
Dynamic: description-content-type
Dynamic: home-page
Dynamic: keywords
Dynamic: license
Dynamic: license-file
Dynamic: project-url
Dynamic: provides-extra
Dynamic: requires-dist
Dynamic: requires-python
Dynamic: summary
